LICENSE.md
README.md
requirements.txt
labours/__init__.py
labours/__main__.py
labours/cli.py
labours/cors_web_server.py
labours/embeddings.py
labours/objects.py
labours/pb_pb2.py
labours/plotting.py
labours/readers.py
labours/utils.py
labours/_vendor/__init__.py
labours/_vendor/swivel.py
labours/modes/__init__.py
labours/modes/burndown.py
labours/modes/devs.py
labours/modes/devs_parallel.py
labours/modes/languages.py
labours/modes/old_vs_new.py
labours/modes/overwrites.py
labours/modes/ownership.py
labours/modes/sentiment.py
labours/modes/shotness.py
labours-10.7.2.dist-info/LICENSE.md
labours-10.7.2.dist-info/METADATA
labours-10.7.2.dist-info/WHEEL
labours-10.7.2.dist-info/entry_points.txt
labours-10.7.2.dist-info/top_level.txt
labours-10.7.2.dist-info/RECORD
