Metadata-Version: 2.1
Name: labours
Version: 10.7.2
Summary: Python companion for github.com/src-d/hercules to visualize the results.
Home-page: https://github.com/src-d/hercules
Author: source{d}
Author-email: machine-learning@sourced.tech
License: Apache-2.0
Download-URL: https://github.com/src-d/hercules
Keywords: git,mloncode,mining software repositories,hercules
Platform: UNKNOWN
Classifier: Development Status :: 5 - Production/Stable
Classifier: Intended Audience :: Developers
Classifier: Environment :: Console
Classifier: License :: OSI Approved :: Apache Software License
Classifier: Programming Language :: Python :: 3.5
Classifier: Programming Language :: Python :: 3.6
Classifier: Programming Language :: Python :: 3.7
Classifier: Programming Language :: Python :: 3.8
Requires-Dist: matplotlib (<4.0,>=2.0)
Requires-Dist: numpy (<2.0,>=1.12.0)
Requires-Dist: pandas (<1.0,>=0.20.0)
Requires-Dist: PyYAML (<6.0,>=3.0)
Requires-Dist: scipy (<1.2.2,>=0.19.0)
Requires-Dist: protobuf (<4.0,>=3.5.0)
Requires-Dist: munch (<3.0,>=2.0)
Requires-Dist: hdbscan (<2.0,>=0.8.0)
Requires-Dist: seriate (<2.0,>=1.1.2)
Requires-Dist: fastdtw (<2.0,>=0.3.2)
Requires-Dist: python-dateutil (<3.0,>=2.6.0)
Requires-Dist: lifelines (<2.0,>=0.20.0)
Requires-Dist: tqdm (<5.0,>=4.3)
